HalfAdder.v
`timescale 1ns / 100ps

module half_adder(
    input x,
    input y,
    output Cout,
    output S
    );

  xor #5 (S,x,y);
  and #5 (Cout,x,y);

endmodule

FullAdder.v
`timescale 1ns / 100ps

module full_adder(
    input A,
    input B,
    input Ci,
    output Cout,
    output S
    );

  wire P,G,H;
  half_adder  ha1(A,B,G,P);
  half_adder  ha2(P,Ci,H,S);
  or #5 (Cout,G,H);

endmodule

FourBitAdder.v
`timescale 1ns/100ps

module FourBitAdder(
    input [3:0] A,
    input [3:0] B,
    output [3:0] S,
    output Cout
    );

  wire C1,C2,C3;

  half_adder ha0(A[0], B[0]    , C1,   S[0]);
  full_adder fa1(A[1], B[1], C1, C2,   S[1]);
  full_adder fa2(A[2], B[2], C2, C3,   S[2]);
  full_adder fa3(A[3], B[3], C3, Cout, S[3]);

endmodule

TestBench.v
`timescale 1ns/100ps

module FourBitAdderTB();
  reg [3:0] A;
  reg [3:0] B;
  wire [4:0] C;
  
  FourBitAdder FBA(
    .A(A),
    .B(B),
    .Cout(C[4]),
    .S(C[3:0])
    );
  
  initial begin 
    $dumpfile("test.vcd"); 
    $dumpvars(1,FourBitAdderTB);  
    #100  A=4'd3; B=4'd4;
    #100  A=4'd0; B=4'd5;
    #100  A=4'd9; B=4'd2;
    #100  A=4'd10; B=4'd10;
    #100  A=4'd15; B=4'd15;
    #100  $finish;
  end
endmodule

test.vcd
$date
	Mon Nov 02 17:26:00 2020
$end
$version
	ModelSim Version 2020.1
$end
$timescale
	100ps
$end

$scope module FourBitAdderTB $end
$var reg 4 ! A [3:0] $end
$var reg 4 " B [3:0] $end
$var wire 1 # C [4] $end
$var wire 1 $ C [3] $end
$var wire 1 % C [2] $end
$var wire 1 & C [1] $end
$var wire 1 ' C [0] $end
$upscope $end
$enddefinitions $end
#0
$dumpvars
bx !
bx "
x'
x&
x%
x$
x#
$end
#1000
b11 !
b100 "
#1050
1'
#1100
1&
#1150
0#
#1200
1%
#1300
0$
#2000
b0 !
b101 "
#2100
0&
#3000
b1001 !
b10 "
#3100
1&
0%
1$
#4000
b1010 !
b1010 "
#4050
0'
#4100
1#
0$
0&
#4150
1%
#5000
b1111 !
b1111 "
#5100
1&
#5150
1$
